{
  "id": 1010957,
  "name": "Orphan-Maker",
  "description": "",
  "modified": "1969-12-31T19:00:00-0500",
  "thumbnail": {
    "path": "http://i.annihil.us/u/prod/marvel/i/mg/c/50/4c7c63f383bac",
    "extension": "jpg"
  },
  "resourceURI": "http://gateway.marvel.com/v1/public/characters/1010957",
  "comics": {
    "available": 0,
    "collectionURI": "http://gateway.marvel.com/v1/public/characters/1010957/comics",
    "items": [],
    "returned": 0
  },
  "series": {
    "available": 0,
    "collectionURI": "http://gateway.marvel.com/v1/public/characters/1010957/series",
    "items": [],
    "returned": 0
  },
  "stories": {
    "available": 0,
    "collectionURI": "http://gateway.marvel.com/v1/public/characters/1010957/stories",
    "items": [],
    "returned": 0
  },
  "events": {
    "available": 0,
    "collectionURI": "http://gateway.marvel.com/v1/public/characters/1010957/events",
    "items": [],
    "returned": 0
  },
  "urls": [
    {
      "type": "detail",
      "url": "http://marvel.com/characters/1669/orphan-maker?utm_campaign=apiRef&utm_source=826a54df0e2b1b28d1a2585efcf9e2b0"
    },
    {
      "type": "wiki",
      "url": "http://marvel.com/universe/Orphan-Maker?utm_campaign=apiRef&utm_source=826a54df0e2b1b28d1a2585efcf9e2b0"
    },
    {
      "type": "comiclink",
      "url": "http://marvel.com/comics/characters/1010957/orphan-maker?utm_campaign=apiRef&utm_source=826a54df0e2b1b28d1a2585efcf9e2b0"
    }
  ]
}