{
  "id": 1010790,
  "name": "Scorpion (Carmilla Black)",
  "description": "Carmilla Black is a genetically engineered human, created by Advanced Idea Mechanics (A.I.M.).",
  "modified": "1969-12-31T19:00:00-0500",
  "thumbnail": {
    "path": "http://i.annihil.us/u/prod/marvel/i/mg/6/40/4c0037366fae7",
    "extension": "jpg"
  },
  "resourceURI": "http://gateway.marvel.com/v1/public/characters/1010790",
  "comics": {
    "available": 5,
    "collectionURI": "http://gateway.marvel.com/v1/public/characters/1010790/comics",
    "items": [
      {
        "resourceURI": "http://gateway.marvel.com/v1/public/comics/1880",
        "name": "Amazing Fantasy (2004) #7"
      },
      {
        "resourceURI": "http://gateway.marvel.com/v1/public/comics/2083",
        "name": "Amazing Fantasy (2004) #9"
      },
      {
        "resourceURI": "http://gateway.marvel.com/v1/public/comics/2515",
        "name": "Incredible Hulk (1999) #87"
      },
      {
        "resourceURI": "http://gateway.marvel.com/v1/public/comics/15925",
        "name": "Incredible Hulk (1999) #108"
      },
      {
        "resourceURI": "http://gateway.marvel.com/v1/public/comics/3007",
        "name": "Scorpion: Poison Tomorrow (Digest)"
      }
    ],
    "returned": 5
  },
  "series": {
    "available": 3,
    "collectionURI": "http://gateway.marvel.com/v1/public/characters/1010790/series",
    "items": [
      {
        "resourceURI": "http://gateway.marvel.com/v1/public/series/769",
        "name": "Amazing Fantasy (2004 - 2006)"
      },
      {
        "resourceURI": "http://gateway.marvel.com/v1/public/series/465",
        "name": "Incredible Hulk (1999 - 2008)"
      },
      {
        "resourceURI": "http://gateway.marvel.com/v1/public/series/1450",
        "name": "Scorpion: Poison Tomorrow (2005)"
      }
    ],
    "returned": 3
  },
  "stories": {
    "available": 4,
    "collectionURI": "http://gateway.marvel.com/v1/public/characters/1010790/stories",
    "items": [
      {
        "resourceURI": "http://gateway.marvel.com/v1/public/stories/1252",
        "name": "1 of 1 -",
        "type": "cover"
      },
      {
        "resourceURI": "http://gateway.marvel.com/v1/public/stories/3640",
        "name": "1 of 6 - Poison Tomorrow",
        "type": "cover"
      },
      {
        "resourceURI": "http://gateway.marvel.com/v1/public/stories/3644",
        "name": "3 of 6 - Poison Tomorrow",
        "type": "cover"
      },
      {
        "resourceURI": "http://gateway.marvel.com/v1/public/stories/32516",
        "name": "World War Hulk 3 of 4; WWH SLUG",
        "type": "cover"
      }
    ],
    "returned": 4
  },
  "events": {
    "available": 1,
    "collectionURI": "http://gateway.marvel.com/v1/public/characters/1010790/events",
    "items": [
      {
        "resourceURI": "http://gateway.marvel.com/v1/public/events/277",
        "name": "World War Hulk"
      }
    ],
    "returned": 1
  },
  "urls": [
    {
      "type": "detail",
      "url": "http://marvel.com/characters/2028/scorpion?utm_campaign=apiRef&utm_source=826a54df0e2b1b28d1a2585efcf9e2b0"
    },
    {
      "type": "wiki",
      "url": "http://marvel.com/universe/Scorpion_%28Carmilla_Black%29?utm_campaign=apiRef&utm_source=826a54df0e2b1b28d1a2585efcf9e2b0"
    },
    {
      "type": "comiclink",
      "url": "http://marvel.com/comics/characters/1010790/scorpion_carmilla_black?utm_campaign=apiRef&utm_source=826a54df0e2b1b28d1a2585efcf9e2b0"
    }
  ]
}